<!DOCTYPE QGLVIEWER>
<QGLViewer version="2.6.1">
  <State stereo="false">
    <foregroundColor red="180" blue="180" green="180"/>
    <backgroundColor red="51" blue="51" green="51"/>
  </State>
  <Display axisIsDrawn="false" gridIsDrawn="false" FPSIsDisplayed="false" cameraIsEdited="false"/>
  <Geometry fullScreen="false" width="1920" posX="0" height="1031" posY="25"/>
  <Camera>
    <Parameters fieldOfView="0.785398" sceneRadius="9.03123" Type="PERSPECTIVE" zNearCoefficient="0.005" orthoCoef="4.02161" zClippingCoefficient="1.73205">
      <SceneCenter x="0" y="0" z="-0.00384127"/>
    </Parameters>
    <Stereo focusDistance="21.8033" physScreenWidth="0.5" IODist="0.062"/>
    <ManipulatedCameraFrame>
      <position x="-8.45237" y="1.00076" z="1.20152"/>
      <orientation q0="0.518272" q1="0.373828" q2="-0.594943" q3="-0.487534"/>
      <ManipulatedParameters transSens="1" zoomSens="1" rotSens="1" wheelSens="1" spinSens="0.3"/>
      <ManipulatedCameraParameters zoomsOnPivotPoint="false" flySpeed="0.0903123" rotatesAroundUpVector="false">
        <sceneUpVector x="0" y="1" z="0"/>
      </ManipulatedCameraParameters>
    </ManipulatedCameraFrame>
  </Camera>
</QGLViewer>
